tdlink/__init__.py
tdlink/core.py
tdlink/datetime_utils.py
tdlink-0.3.dist-info/METADATA
tdlink-0.3.dist-info/RECORD
tdlink-0.3.dist-info/WHEEL
tdlink-0.3.dist-info/top_level.txt
