Metadata-Version: 2.1
Name: tdlink
Version: 0.3
Summary: Python Library for TDAmeritrade API
Home-page: https://github.com/ysriram1/tdlink
Author: Sriram Yarlagadda
Author-email: ysriram@umich.edu
License: MIT
Platform: UNKNOWN
Classifier: Programming Language :: Python :: 3
Classifier: License :: OSI Approved :: MIT License
Classifier: Operating System :: OS Independent
